pyduckling_native-0.1.0.dist-info/RECORD
pyduckling_native-0.1.0.dist-info/LICENSE
pyduckling_native-0.1.0.dist-info/WHEEL
pyduckling_native-0.1.0.dist-info/top_level.txt
pyduckling_native-0.1.0.dist-info/METADATA
duckling/__init__.py
duckling/duckling.cpython-37m-darwin.so
duckling/tests/test_duckling.py
duckling/tests/__init__.py
duckling/.dylibs/libHSuuid-types-1.0.3-Autqzm2g4auIYSV6nkCRLV-ghc8.6.5.dylib
duckling/.dylibs/libpcre.1.dylib
duckling/.dylibs/libHSscientific-0.3.6.2-BboXwnuKby4BtCVtfss4TP-ghc8.6.5.dylib
duckling/.dylibs/libHSdirectory-1.3.3.0-ghc8.6.5.dylib
duckling/.dylibs/libHSpretty-1.1.3.6-ghc8.6.5.dylib
duckling/.dylibs/libHSaeson-1.4.4.0-1fGrbMT85MxLFyTOIpx2Qj-ghc8.6.5.dylib
duckling/.dylibs/libHSghc-boot-th-8.6.5-ghc8.6.5.dylib
duckling/.dylibs/libHSarray-0.5.3.0-ghc8.6.5.dylib
duckling/.dylibs/libHSinteger-logarithms-1.0.3-4fjS4bKV0939VXcQKK2I7B-ghc8.6.5.dylib
duckling/.dylibs/libHSprimitive-0.6.4.0-ILgywxtLpvnAOlEISPpP5b-ghc8.6.5.dylib
duckling/.dylibs/libHSfilepath-1.4.2.1-ghc8.6.5.dylib
duckling/.dylibs/libHStemplate-haskell-2.14.0.0-ghc8.6.5.dylib
duckling/.dylibs/libHSunix-2.7.2.2-ghc8.6.5.dylib
duckling/.dylibs/libHStimezone-series-0.1.9-GLpW8QdZnrsAedsxpempxm-ghc8.6.5.dylib
duckling/.dylibs/libHSghc-prim-0.5.3-ghc8.6.5.dylib
duckling/.dylibs/libHSdlist-0.8.0.7-62vR0IWGKydvDRbWJTrKt-ghc8.6.5.dylib
duckling/.dylibs/libHScontainers-0.6.0.1-ghc8.6.5.dylib
duckling/.dylibs/libHSvector-0.12.0.3-LfvlcMFJAcY18uD1Y2O5Ig-ghc8.6.5.dylib
duckling/.dylibs/libHSclock-0.8-H1S1zDefxirImaRbI6ITNv-ghc8.6.5.dylib
duckling/.dylibs/libHShashable-1.2.7.0-2SI038axTEd7AEZJ275kpi-ghc8.6.5.dylib
duckling/.dylibs/libHStime-1.8.0.2-ghc8.6.5.dylib
duckling/.dylibs/libHSregex-base-0.93.2-6BO9nGUPmsrJWZAlHnRAU-ghc8.6.5.dylib
duckling/.dylibs/libHStimezone-olson-0.1.9-KqfH84wsL3w8Wy0pNSNbjG-ghc8.6.5.dylib
duckling/.dylibs/libducklingffi.so
duckling/.dylibs/libHSdependent-sum-0.4-DC6FPbMlBM3GVVz1DTobQQ-ghc8.6.5.dylib
duckling/.dylibs/libHSrandom-1.1-3ypV4EIycgb35PKjTYYr5q-ghc8.6.5.dylib
duckling/.dylibs/libHStime-compat-1.9.2.2-2s4hxMUsPxYAh4bvYaYAFK-ghc8.6.5.dylib
duckling/.dylibs/libHStransformers-0.5.6.2-ghc8.6.5.dylib
