Metadata-Version: 2.1
Name: pyduckling-native
Version: 0.1.0
Summary: Rust-based Python wrapper for duckling library in Haskell.
Home-page: https://github.com/treble-ai/pyduckling
Author: Edgar Andrés Margffoy Tuay
Author-email: andfoy@gmail.com
License: MIT
Keywords: haskell,python,parse,duckling
Platform: UNKNOWN
Classifier: Development Status :: 4 - Beta
Classifier: Intended Audience :: Developers
Classifier: License :: OSI Approved :: MIT License
Classifier: Programming Language :: Python :: 3.5
Classifier: Programming Language :: Python :: 3.6
Classifier: Programming Language :: Python :: 3.7
Classifier: Programming Language :: Python :: 3.8
